LICENSE
README.md
setup.py
elbus/__init__.py
elbus/client.py
elbus/rpc.py
elbus.egg-info/PKG-INFO
elbus.egg-info/SOURCES.txt
elbus.egg-info/dependency_links.txt
elbus.egg-info/top_level.txt