Metadata-Version: 2.1
Name: elbus
Version: 0.0.15
Summary: python client for elbus (sync)
Home-page: https://github.com/alttch/elbus
Author: Bohemia Automation / Altertech
Author-email: div@altertech.com
License: MIT
Platform: UNKNOWN
Classifier: Programming Language :: Python :: 3
Classifier: License :: OSI Approved :: MIT License
Classifier: Topic :: Software Development :: Libraries
Classifier: Topic :: Communications
License-File: LICENSE
